{
  "$ref": "#/definitions/TraceContextPropagation",
  "definitions": {
    "TraceContextPropagation": {
      "type": "object",
      "properties": {
        "formats": {
          "type": "array",
          "items": {
            "type": "string",
            "enum": [
              "w3c",
              "b3",
              "b3_multi",
              "jaeger",
              "xray",
              "ottrace",
              "custom"
            ],
            "description": "Trace propagation format"
          },
          "default": [
            "w3c"
          ]
        },
        "extract": {
          "type": "boolean",
          "default": true
        },
        "inject": {
          "type": "boolean",
          "default": true
        },
        "headers": {
          "type": "object",
          "properties": {
            "traceId": {
              "type": "string"
            },
            "spanId": {
              "type": "string"
            },
            "traceFlags": {
              "type": "string"
            },
            "traceState": {
              "type": "string"
            }
          },
          "additionalProperties": false
        },
        "baggage": {
          "type": "object",
          "properties": {
            "enabled": {
              "type": "boolean",
              "default": true
            },
            "maxSize": {
              "type": "integer",
              "exclusiveMinimum": 0,
              "default": 8192
            },
            "allowedKeys": {
              "type": "array",
              "items": {
                "type": "string"
              }
            }
          },
          "additionalProperties": false
        }
      },
      "additionalProperties": false,
      "description": "Trace context propagation"
    }
  },
  "$schema": "http://json-schema.org/draft-07/schema#"
}